get_car_info/__init__.py
get_car_info/api/__init__.py
get_car_info/api/car_info.py
get_car_info/models/__init__.py
get_car_info/models/car_model.py
get_car_info-1.0.1.dist-info/LICENSE
get_car_info-1.0.1.dist-info/METADATA
get_car_info-1.0.1.dist-info/WHEEL
get_car_info-1.0.1.dist-info/RECORD
