Metadata-Version: 2.3
Name: get-car-info
Version: 1.0.1
Summary: Поиск информации по госномеру
Author: mayn3r
Author-email: mayneryt@bk.ru
Requires-Python: >=3.10
Classifier: Programming Language :: Python :: 3
Classifier: Programming Language :: Python :: 3.10
Classifier: Programming Language :: Python :: 3.11
Classifier: Programming Language :: Python :: 3.12
Classifier: Programming Language :: Python :: 3.13
Requires-Dist: bs4 (>=0.0.2,<0.0.3)
Requires-Dist: lxml (>=5.3.0,<6.0.0)
Requires-Dist: pydantic (==2.10.6)
Requires-Dist: requests (>=2.32.3,<3.0.0)
